KD_Lib/__init__.py
KD_Lib/KD/__init__.py
KD_Lib/KD/common/__init__.py
KD_Lib/KD/common/base_class.py
KD_Lib/KD/text/__init__.py
KD_Lib/KD/text/BERT2LSTM/__init__.py
KD_Lib/KD/text/BERT2LSTM/bert2lstm.py
KD_Lib/KD/text/BERT2LSTM/utils.py
KD_Lib/KD/text/utils/__init__.py
KD_Lib/KD/text/utils/bert.py
KD_Lib/KD/vision/__init__.py
KD_Lib/KD/vision/BANN/BANN.py
KD_Lib/KD/vision/BANN/__init__.py
KD_Lib/KD/vision/CSKD/__init__.py
KD_Lib/KD/vision/CSKD/cskd.py
KD_Lib/KD/vision/CSKD/sampler.py
KD_Lib/KD/vision/DML/__init__.py
KD_Lib/KD/vision/DML/dml.py
KD_Lib/KD/vision/KA/LSR.py
KD_Lib/KD/vision/KA/PS.py
KD_Lib/KD/vision/KA/__init__.py
KD_Lib/KD/vision/RCO/__init__.py
KD_Lib/KD/vision/RCO/rco.py
KD_Lib/KD/vision/RKD/__init__.py
KD_Lib/KD/vision/RKD/loss_metric.py
KD_Lib/KD/vision/TAKD/__init__.py
KD_Lib/KD/vision/TAKD/takd.py
KD_Lib/KD/vision/attention/__init__.py
KD_Lib/KD/vision/attention/attention.py
KD_Lib/KD/vision/attention/loss_metric.py
KD_Lib/KD/vision/mean_teacher/__init__.py
KD_Lib/KD/vision/mean_teacher/mean_teacher.py
KD_Lib/KD/vision/noisy/__init__.py
KD_Lib/KD/vision/noisy/messy_collab.py
KD_Lib/KD/vision/noisy/noisy_teacher.py
KD_Lib/KD/vision/noisy/soft_random.py
KD_Lib/KD/vision/noisy/utils.py
KD_Lib/KD/vision/teacher_free/__init__.py
KD_Lib/KD/vision/teacher_free/self_training.py
KD_Lib/KD/vision/teacher_free/virtual_teacher.py
KD_Lib/KD/vision/vanilla/__init__.py
KD_Lib/KD/vision/vanilla/vanilla_kd.py
KD_Lib/Pruning/__init__.py
KD_Lib/Pruning/common/__init__.py
KD_Lib/Pruning/common/iterative_base_class.py
KD_Lib/Pruning/lottery_tickets/__init__.py
KD_Lib/Pruning/lottery_tickets/lottery_tickets.py
KD_Lib/Pruning/weight_threshold/__init__.py
KD_Lib/Pruning/weight_threshold/weight_threshold_pruning.py
KD_Lib/Quantization/__init__.py
KD_Lib/Quantization/common/__init__.py
KD_Lib/Quantization/common/base_class.py
KD_Lib/Quantization/dynamic/__init__.py
KD_Lib/Quantization/dynamic/dynamic_quantization.py
KD_Lib/Quantization/qat/__init__.py
KD_Lib-0.0.32.dist-info/LICENSE
KD_Lib-0.0.32.dist-info/METADATA
KD_Lib-0.0.32.dist-info/WHEEL
KD_Lib-0.0.32.dist-info/top_level.txt
KD_Lib-0.0.32.dist-info/RECORD
