Metadata-Version: 2.1
Name: KD-Lib
Version: 0.0.32
Summary: A PyTorch model compression library containing easy-to-use methods for knowledge distillation, pruning, and quantization
Home-page: https://github.com/SforAiDL/KD_Lib
Author: Het Shah
Author-email: divhet163@gmail.com
License: MIT license
Keywords: Knowledge Distillation,Pruning,Quantization,pytorch,machine learning,deep learning
Classifier: Development Status :: 2 - Pre-Alpha
Classifier: Intended Audience :: Developers
Classifier: License :: OSI Approved :: MIT License
Classifier: Natural Language :: English
Classifier: Programming Language :: Python :: 3.6
Classifier: Programming Language :: Python :: 3.7
License-File: LICENSE
Requires-Dist: pip (==21.1)
Requires-Dist: transformers (==4.6.1)
Requires-Dist: sacremoses
Requires-Dist: tokenizers (==0.10.1)
Requires-Dist: huggingface-hub (==0.0.8)
Requires-Dist: torchtext (==0.9.1)
Requires-Dist: bumpversion (==0.5.3)
Requires-Dist: wheel (==0.32.1)
Requires-Dist: watchdog (==0.9.0)
Requires-Dist: flake8 (==3.5.0)
Requires-Dist: tox (==3.5.2)
Requires-Dist: coverage (==4.5.1)
Requires-Dist: Sphinx (==1.8.1)
Requires-Dist: twine (==1.12.1)
Requires-Dist: pytest (==3.8.2)
Requires-Dist: pytest-runner (==4.2)
Requires-Dist: pytest-cov (==2.6.1)
Requires-Dist: matplotlib (==3.2.1)
Requires-Dist: torch (==1.8.1)
Requires-Dist: torchvision (==0.9.1)
Requires-Dist: tensorboard (==2.2.1)
Requires-Dist: contextlib2 (==0.6.0.post1)
Requires-Dist: pandas (==1.0.1)
Requires-Dist: tqdm (==4.42.1)
Requires-Dist: numpy (==1.21.0)
Requires-Dist: sphinx-rtd-theme (==0.5.0)
